microjax/__init__.py
microjax/engine.py
microjax/nn.py
microjax-0.1.0.dist-info/METADATA
microjax-0.1.0.dist-info/WHEEL
microjax-0.1.0.dist-info/licenses/LICENSE
microjax-0.1.0.dist-info/RECORD
