Metadata-Version: 2.4
Name: microjax
Version: 0.1.0
Summary: Like Karpathy's micrograd but following JAX's functional style
Project-URL: Repository, https://github.com/chuan97/microjax
License-Expression: MIT
License-File: LICENSE
Requires-Python: >3.11
